tuixdate/__init__.py
tuixdate/common.py
tuixdate/globals.py
tuixdate/logger.py
tuixdate/main.py
tuixdate/utils.py
tuixdate/clients/__init__.py
tuixdate/clients/trello_client.py
tuixdate/clients/tuix.py
tuixdate/commands/__init__.py
tuixdate/commands/clean.py
tuixdate/commands/list.py
tuixdate/commands/login.py
tuixdate/commands/projects.py
tuixdate/commands/push.py
tuixdate/commands/send.py
tuixdate/commands/timesheet.py
tuixdate/commands/trello.py
tuixdate/commands/version.py
tuixdate-0.0.3.dist-info/METADATA
tuixdate-0.0.3.dist-info/WHEEL
tuixdate-0.0.3.dist-info/entry_points.txt
tuixdate-0.0.3.dist-info/top_level.txt
tuixdate-0.0.3.dist-info/RECORD
