Metadata-Version: 2.1
Name: tuixdate
Version: 0.0.3
Summary: Tuix Timesheet
Home-page: https://github.com/tuixdevelopment/tuixdate
Author: Ericson Joseph
Author-email: ericson.estupinnan@tuix.ch
License: MIT
Platform: UNKNOWN
Classifier: Development Status :: 5 - Production/Stable
Classifier: Intended Audience :: Developers
Classifier: Topic :: Software Development :: Build Tools
Classifier: Programming Language :: Python :: 3.7
Classifier: Programming Language :: Python :: 3.8
Classifier: Programming Language :: Python :: 3.9
Classifier: Programming Language :: Python :: 3 :: Only
Classifier: License :: OSI Approved :: MIT License
Classifier: Operating System :: OS Independent
Requires-Python: >=3.7
Requires-Dist: tabulate
Requires-Dist: certifi
